{
  "title": " Kagurabachi",
  "description": "Young Chihiro spends his days training under his famous swordsmith father. One day he hopes to become a great sword-maker himself. The goofy father and the serious son--they thought these days would last forever. But suddenly, tragedy strikes. A dark day soaked in blood. Chihiro and his blade now live only for revenge.",
  "artist": "Hokazono Takeru",
  "author": "Hokazono Takeru",
  "cover": "",
  "chapters": {
    "111": {
      "title": "111",
      "volume": "",
      "last_updated": "1770500871",
      "groups": {
        "@EkzoTeam": [
          "https://drive.usercontent.google.com/download?id=1xXjAXgZeALL_15Dui0zbNrxcGRnt4VpY",
          "https://drive.usercontent.google.com/download?id=1IHkISYRbSgC7QCgEg4yMYoGJcuV8qknd",
          "https://drive.usercontent.google.com/download?id=1XJoTokpx-WvdA7p9IEAwOeByHF44IcWc"
        ]
      }
    }
  }
}